{
  "id": 94,
  "lastModified": "2024-09-11 12:36:56",
  "authType": 1,
  "method": "GET/POST",
  "path": "alibaba.icbu.product.schema.get",
  "common": [
    {
      "treeId": null,
      "data": [],
      "children": [],
      "name": "app_key",
      "id": null,
      "type": "String",
      "required": true,
      "desc": "Unique app ID issued by ICBU Open Platform console when you apply for an app category"
    },
    {
      "treeId": null,
      "data": [],
      "children": [],
      "name": "timestamp",
      "id": null,
      "type": "String",
      "required": true,
      "desc": "The time stamp of the request e.g. 1517820392000 (which translates to 5 February 2018 08:46:32) with less than 7200s difference from UTC time"
    },
    {
      "treeId": null,
      "data": [],
      "children": [],
      "name": "access_token",
      "id": null,
      "type": "String",
      "required": true,
      "desc": "API interface call credentials"
    },
    {
      "treeId": null,
      "data": [],
      "children": [],
      "name": "sign_method",
      "id": null,
      "type": "String",
      "required": true,
      "desc": "The HMAC hash algorithm you are using to calculate your signature"
    },
    {
      "treeId": null,
      "data": [],
      "children": [],
      "name": "sign",
      "id": null,
      "type": "String",
      "required": true,
      "desc": "Part of the authentication process that is used for identifying and verifying who is sending a request (click <a target='_blank' href='https://open.alibaba.com/doc.htm?docId=107468&docType=1'>here</a> for details)"
    }
  ],
  "sdk": "",
  "http": ""
}